pyrfa/RDMFieldDictionary
pyrfa/__init__.py
pyrfa/enumtype.def
pyrfa/pyrfa.pyd
pyrfa-8.5.3.dist-info/METADATA
pyrfa-8.5.3.dist-info/RECORD
pyrfa-8.5.3.dist-info/WHEEL
pyrfa-8.5.3.dist-info/top_level.txt
