Metadata-Version: 2.1
Name: pyrfa
Version: 8.5.3
Summary: Python API for Refinitiv (Thomson Reuters) Enterprise Platform
Home-page: https://github.com/devcartel/pyrfa
Author: DevCartel
Author-email: support@devcartel.com
License: MIT
Keywords: refinitiv thomson reuters enterprise python rfa api feed elektron trep rmds rdfd ats market data
Platform: UNKNOWN
Classifier: Development Status :: 5 - Production/Stable
Classifier: Intended Audience :: Developers
Classifier: Topic :: Software Development :: Build Tools
Classifier: License :: OSI Approved :: MIT License
Classifier: Programming Language :: Python :: 2
Classifier: Programming Language :: Python :: 2.6
Classifier: Programming Language :: Python :: 2.7
Classifier: Programming Language :: Python :: 3
Classifier: Programming Language :: Python :: 3.4
Classifier: Programming Language :: Python :: 3.5
Classifier: Programming Language :: Python :: 3.6
Classifier: Programming Language :: Python :: 3.7
